sqlfluff_common_conventions/CC01.py
sqlfluff_common_conventions/CC02.py
sqlfluff_common_conventions/CC03.py
sqlfluff_common_conventions/CC04.py
sqlfluff_common_conventions/CC05.py
sqlfluff_common_conventions/CC06.py
sqlfluff_common_conventions/__init__.py
sqlfluff_common_conventions/plugin_default_config.cfg
sqlfluff_common_conventions-0.4.0.dist-info/LICENSE
sqlfluff_common_conventions-0.4.0.dist-info/METADATA
sqlfluff_common_conventions-0.4.0.dist-info/WHEEL
sqlfluff_common_conventions-0.4.0.dist-info/entry_points.txt
sqlfluff_common_conventions-0.4.0.dist-info/top_level.txt
sqlfluff_common_conventions-0.4.0.dist-info/RECORD
