Metadata-Version: 2.1
Name: sqlfluff_common_conventions
Version: 0.4.0
Summary: An SQLFluff plugin for rules that enforce common SQL naming conventions.
Author-email: Valerie Tan <valerietanhx@gmail.com>
License: MIT License
Keywords: sqlfluff,sql,linter,formatter,bigquery,databricks,postgres,postgresql
Classifier: Intended Audience :: Developers
Classifier: Development Status :: 3 - Alpha
Classifier: License :: OSI Approved :: MIT License
Classifier: Operating System :: Unix
Classifier: Operating System :: POSIX
Classifier: Operating System :: MacOS
Classifier: Operating System :: Microsoft :: Windows
Classifier: Programming Language :: Python
Classifier: Programming Language :: Python :: 3
Classifier: Programming Language :: Python :: 3.8
Classifier: Programming Language :: Python :: 3.9
Classifier: Programming Language :: Python :: 3.10
Classifier: Programming Language :: Python :: 3.11
Classifier: Programming Language :: Python :: 3.12
Classifier: Programming Language :: Python :: Implementation :: CPython
Classifier: Programming Language :: SQL
Classifier: Topic :: Utilities
Classifier: Topic :: Software Development :: Quality Assurance
Requires-Python: >=3.8
License-File: LICENSE
Requires-Dist: sqlfluff >=0.4.0
